client_model/__init__.py
client_model/client.py
examples/demo.py
tests/test_client.py
client_model-0.2.0.dist-info/METADATA
client_model-0.2.0.dist-info/WHEEL
client_model-0.2.0.dist-info/top_level.txt
client_model-0.2.0.dist-info/RECORD
