Metadata-Version: 2.4
Name: client_model
Version: 0.2.0
Summary: Pacote de exemplo com clientes e operações bancárias
Author-email: Michael Baldez <mikebaldez75@gmail.com>
License: MIT
Classifier: Programming Language :: Python :: 3
Classifier: Operating System :: OS Independent
Requires-Python: >=3.8
